repomap/__init__.py
repomap/ast_grep_utils.py
repomap/callstack.py
repomap/cli.py
repomap/config.py
repomap/core.py
repomap/providers.py
repomap/queries/tree-sitter-c-tags.scm
repomap/queries/tree-sitter-c_sharp-tags.scm
repomap/queries/tree-sitter-cpp-tags.scm
repomap/queries/tree-sitter-go-tags.scm
repomap/queries/tree-sitter-java-tags.scm
repomap/queries/tree-sitter-javascript-tags.scm
repomap/queries/tree-sitter-php-tags.scm
repomap/queries/tree-sitter-python-tags.scm
repomap/repo_tree.py
repomap/schemas.py
repomap/utils.py
repomap_suite-0.2.0.dist-info/LICENSE
repomap_suite-0.2.0.dist-info/METADATA
repomap_suite-0.2.0.dist-info/WHEEL
repomap_suite-0.2.0.dist-info/entry_points.txt
repomap_suite-0.2.0.dist-info/RECORD
