Metadata-Version: 2.1
Name: repomap-suite
Version: 0.2.0
Summary: 
Author: Stanislav
Author-email: goncharuk.sm@yandex.ru
Requires-Python: >=3.12,<4.0
Classifier: Programming Language :: Python :: 3
Classifier: Programming Language :: Python :: 3.12
Requires-Dist: ast-grep-cli (==0.39.5)
Requires-Dist: ast-grep-py (>=0.30.0,<0.31.0)
Requires-Dist: gitpython (>=3.1.45,<4.0.0)
Requires-Dist: pydantic-settings (>=2.7.1,<3.0.0)
Requires-Dist: pygithub (>=2.5.0,<3.0.0)
Requires-Dist: python-dotenv (>=1.0.1,<2.0.0)
Requires-Dist: python-gitlab (>=4.4.0,<5.0.0)
Requires-Dist: requests (>=2.32.3,<3.0.0)
Requires-Dist: setuptools (>=75.8.0,<76.0.0)
Requires-Dist: tree-sitter (==0.21.3)
Requires-Dist: tree-sitter-languages (>=1.10.2,<2.0.0)
Requires-Dist: types-requests (>=2.32.0.20241016,<3.0.0.0)
